setup.py
salure_helpers/mysql/__init__.py
salure_helpers/mysql/mysql.py
salure_helpers_mysql.egg-info/PKG-INFO
salure_helpers_mysql.egg-info/SOURCES.txt
salure_helpers_mysql.egg-info/dependency_links.txt
salure_helpers_mysql.egg-info/not-zip-safe
salure_helpers_mysql.egg-info/requires.txt
salure_helpers_mysql.egg-info/top_level.txt