Metadata-Version: 1.0
Name: salure-helpers-mysql
Version: 1.0.4
Summary: MySQL wrapper from Salure
Home-page: UNKNOWN
Author: D&A Salure
Author-email: support@salureconnnect.com
License: Salure License
Platform: UNKNOWN
